LICENSE
frelatage/__init__.py
frelatage/_cycle.py
frelatage/_evaluate.py
frelatage/_fuzz.py
frelatage/_input.py
frelatage/_interface.py
frelatage/_mutation.py
frelatage/_report.py
frelatage/colors.py
frelatage/config/__init__.py
frelatage/config/config.py
frelatage/corpus/__init__.py
frelatage/corpus/corpus.py
frelatage/dictionary/__init__.py
frelatage/dictionary/dictionary.py
frelatage/input/__init__.py
frelatage/input/input.py
frelatage/mutator/__init__.py
frelatage/mutator/dictionary.py
frelatage/mutator/magicValues.py
frelatage/mutator/mutator.py
frelatage/queue/__init__.py
frelatage/queue/queue.py
frelatage/report/__init__.py
frelatage/report/report.py
frelatage/tracer/__init__.py
frelatage/tracer/trace_result.py
frelatage/tracer/tracer.py
scripts/read_report.py
frelatage-0.1.7.dist-info/entry_points.txt
frelatage-0.1.7.dist-info/LICENSE
frelatage-0.1.7.dist-info/WHEEL
frelatage-0.1.7.dist-info/METADATA
frelatage-0.1.7.dist-info/RECORD
