Metadata-Version: 2.1
Name: frelatage
Version: 0.1.7
Summary: Frelatage is a coverage-based Python fuzzing library which can be used to fuzz python code.
Home-page: https://github.com/Rog3rSm1th/Frelatage
License: MIT
Keywords: frelatage,fuzzer
Author: Rog3rSm1th
Author-email: r0g3r5@protonmail.com
Requires-Python: >=3.9,<4.0
Classifier: Environment :: Console
Classifier: License :: OSI Approved :: MIT License
Classifier: Programming Language :: Python :: 3
Classifier: Programming Language :: Python :: 3.10
Classifier: Programming Language :: Python :: 3.9
Requires-Dist: Pympler (>=1.0.1,<2.0.0)
Requires-Dist: numpy (>=1.22.3,<2.0.0)
Requires-Dist: timeout-decorator (>=0.5.0,<0.6.0)
Project-URL: Repository, https://github.com/Rog3rSm1th/Frelatage
